<annotation>
	<folder>my</folder>
	<filename>my.0fdf011d-b6f0-11ed-9034-5c879c62795a.jpg</filename>
	<path>C:\Users\danie\OneDrive\Desktop\University\Computer Science\Programming\TFOD\TFODCourse\Tensorflow\workspace\images\family\my\my.0fdf011d-b6f0-11ed-9034-5c879c62795a.jpg</path>
	<source>
		<database>Unknown</database>
	</source>
	<size>
		<width>640</width>
		<height>480</height>
		<depth>3</depth>
	</size>
	<segmented>0</segmented>
	<object>
		<name>my</name>
		<pose>Unspecified</pose>
		<truncated>0</truncated>
		<difficult>0</difficult>
		<bndbox>
			<xmin>270</xmin>
			<ymin>349</ymin>
			<xmax>342</xmax>
			<ymax>456</ymax>
		</bndbox>
	</object>
</annotation>
